DenoEngine/__init__.py
DenoEngine/core.py
DenoEngine/objects.py
DenoEngine/ui.py
denoengine-0.3.0.dist-info/METADATA
denoengine-0.3.0.dist-info/WHEEL
denoengine-0.3.0.dist-info/top_level.txt
denoengine-0.3.0.dist-info/RECORD
